break_axes/__init__.py
break_axes/break_axes.py
break_axes-0.4.0.dist-info/licenses/LICENSE
break_axes-0.4.0.dist-info/METADATA
break_axes-0.4.0.dist-info/WHEEL
break_axes-0.4.0.dist-info/top_level.txt
break_axes-0.4.0.dist-info/RECORD
