Metadata-Version: 2.4
Name: break_axes
Version: 0.4.0
Summary: A Matplotlib-based utility module for creating broken axes.
Author-email: Wu Yao <wuyao2020@gmail.com>
License-Expression: MIT
Project-URL: Homepage, https://github.com/wuyao1997/break_axes
Project-URL: Source, https://github.com/wuyao1997/break_axes
Project-URL: Documentation, https://github.com/wuyao1997/break_axes/wiki
Classifier: Programming Language :: Python :: 3
Classifier: Operating System :: OS Independent
Classifier: Framework :: Matplotlib
Requires-Python: >=3.8
License-File: LICENSE
Requires-Dist: matplotlib>=3.0.0
Dynamic: license-file
